Workbook

Sheet Overview
A1: Mystic Companion — Business Plan
A2: Zodiac companion app · tarot · moon calendar · collectible minerals · subscription + coins/gems economy
A4: The Pitch
A5: A daily-habit app for people who love astrology, tarot, and crystals — built around a personal Zodiac Companion that talks to you, reads for you, and grows with you. Free to start, funny and self-aware about the hustle, and monetized like a game: a subscription for depth, a coins-and-gems economy for the collector/gacha loop, and a premium Compatibility feature as the big unlock once you've told the app enough about yourself.
A10: Who This Is For
A11: Primary audience | B11: Women 18–34 into astrology, tarot, crystals, manifestation, witchy/cottagecore aesthetics — active on TikTok and Instagram.
A12: Secondary audience | B12: Anyone who reads their horoscope 'ironically' but checks it daily anyway; gift-givers buying a subscription for a friend.
A13: Tone | B13: Sincere enough to feel real, funny enough to admit it's a business. The companion breaks the fourth wall about money — that's the brand, not a bug.
A14: Comparable apps | B14: Co-Star, The Pattern, Sanctuary, Nebula — all proved the category. Our wedge is the game-like collection/currency layer and the companion-chat relationship none of them fully lean into.
A16: How This Workbook Is Organized
A17: What We've Built | B17: Status of the actual app scaffold already in the repo.
A18: Free vs Premium | B18: Full feature matrix across the three tiers.
A19: Coins & Gems Economy | B19: How the soft/hard currency loop works — earn and spend.
A20: Shop Catalog | B20: Every purchasable item, its price, and which currency it uses.
A21: Chat & Companion | B21: The chat feature spec and its monetization.
A22: Content Calendar | B22: Daily/weekly/yearly content cadence and ownership.
A23: Revenue Assumptions | B23: Every input the financial model uses — edit these to re-run the plan.
A24: Financial Projections | B24: 12-month revenue model driven by the assumptions.
A25: Unit Economics | B25: LTV, CAC, payback period.
A26: Target Audience & Marketing | B26: Positioning, channels, competitor snapshot.
A27: Roadmap | B27: Build phases from today to a mature product.

Sheet What We've Built
A1: What We've Built
A2: Status of the working app scaffold (React + Vite + Tailwind) already committed to the repo.
A4: Screen / System | B4: What it does | C4: Status | D4: Notes
A5: Onboarding | B5: Collects name + birth date, computes sun sign live | C5: Working | D5: Client-side only, no account system yet
A6: Home / Companion | B6: Greets user, shows free daily word + locked premium reading | C6: Working (mock content) | D6: 12 signs of mock copy; needs real/AI-generated content pipeline
A7: Moon Calendar | B7: Real astronomical moon-phase math, current + next 4 major phases, ritual suggestion | C7: Working (real data) | D7: Genuinely accurate lunar math, not decorative
A8: Tarot | B8: Daily free single-card draw + premium 3-card spread | C8: Working (mock deck) | D8: 12-card mock deck; needs full 78-card deck + real art
A9: Minerals | B9: Collectible grid, rarity tiers, premium-gated rares, undiscovered = '???' | C9: Working (mock data) | D9: 10 mock minerals; this is the gacha/collection engine
A10: Compatibility | B10: Element-based compatibility score between two birth dates, gated behind Premium + Dossier completion | C10: Working (calculator only) | D10: Deliberately NOT user-to-user matching — see Roadmap
A11: Profile / Dossier | B11: Progressive personal-info form with a completion meter | C11: Working | D11: This is the funnel that unlocks Compatibility
A12: Upgrade / Paywall | B12: Three subscription tiers, in-voice copy, mock plan selector | C12: Working (no real payment) | D12: Needs Stripe Billing integration
A13: Companion Chat | B13: Chat with your Zodiac Companion | C13: Not built yet | D13: See 'Chat & Companion' tab for full spec
A14: Coins & Gems | B14: Dual-currency economy, shop, wallet | C14: Not built yet | D14: See 'Coins & Gems Economy' + 'Shop Catalog' tabs
A15: Backend / Accounts | B15: Real auth, database, cross-device sync | C15: Not built yet | D15: Currently everything persists to browser localStorage only
A16: Payments | B16: Real subscription billing + gem-pack purchases | C16: Not built yet | D16: Needs Stripe (web) and/or RevenueCat (if native mobile later)
A18: Tech Stack (current)
A19: Frontend | B19: React 19 + TypeScript + Vite, Tailwind CSS v4, React Router
A20: State | B20: React Context + localStorage (placeholder until a real backend exists)
A21: Platform | B21: Web app / PWA first — simpler billing via Stripe, fastest to iterate, wraps into React Native later if native mobile is worth it

Sheet Free vs Premium
A1: Free vs Premium — Feature Matrix
A2: Three tiers: Apprentice (free), Mystic, Oracle. This is the paywall map for the whole product.
A4: Feature | B4: Apprentice (Free) | C4: Mystic — $4.99/mo | D4: Oracle — $9.99/mo
A5: Daily word (short) | B5: Yes | C5: Yes | D5: Yes
A6: Daily reading (full/deep) | B6: No | C6: Yes | D6: Yes
A7: Weekly theme reading | B7: No | C7: Yes | D7: Yes
A8: Yearly forecast | B8: Buy with Gems (one-time) | C8: Buy with Gems (discounted) | D8: Included
A9: Moon calendar + phase tracking | B9: Yes | C9: Yes | D9: Yes
A10: Moon ritual suggestions | B10: Basic | C10: Full | D10: Full + reminders
A11: Tarot: daily single card | B11: Yes | C11: Yes | D11: Yes
A12: Tarot: 3-card spread | B12: No | C12: Yes | D12: Yes
A13: Tarot: Celtic Cross spread | B13: No | C13: No | D13: Yes
A14: Mineral pulls — Common/Uncommon | B14: Yes, via Coins | C14: Yes, faster drop rate | D14: Yes, faster drop rate
A15: Mineral pulls — Rare/Legendary | B15: Gems only | C15: Gems (discounted) | D15: 1 guaranteed Rare+ pull/month included
... A21: Shareable daily-word cards | B21: Yes (this is free user-acquisition) | C21: Yes, extra templates | D21: Yes, extra templates
A23: Why the Paywall Sits Where It Does
A24: • Compatibility is gated behind BOTH Premium and a completed Dossier — completing your profile is free and fun, and it's also exactly the data that makes Compatibility (and future personalization) good. The paywall arrives right when the payoff is biggest.
A25: • The free tier is generous on breadth (every feature exists for free users in some form) but shallow on depth — this keeps free users engaged and sharing (acquisition) while the 'more/better/faster' upsell stays constant and visible, never a hard wall.
A26: • Rare/Legendary minerals are real-money-adjacent (Gems) even for subscribers, because collectible rarity is the single strongest whale-monetization lever in the whole product — protect it.

Sheet Coins & Gems Economy
A1: Coins & Gems Economy
A2: Dual-currency system, standard for collectible/gacha-style mobile games. Coins = earned, soft currency. Gems = premium, hard currency.
A4: 🪙 Coins — how you earn them
A5: Action | B5: Coins Earned | C5: Purpose
A6: Daily login | B6: 10 | C6: Baseline habit reward
A7: Complete daily tarot draw | B7: 5 | C7: Reinforces daily open
A8: Complete daily horoscope read | B8: 5 | C8: Reinforces daily open
A9: 7-day login streak bonus | B9: 50 | C9: Retention — protects the streak
A10: Fill one Dossier field (one-time each) | B10: 25 | C10: Drives profile completion → Compatibility funnel
A11: Share a daily-word card socially | B11: 15 | C11: Free user acquisition, paid in Coins not cash
A12: Weekly quest completion | B12: 30–75 | C12: Weekly re-engagement loop
A13: Watch a rewarded ad (free users only) | B13: 20 | C13: Optional monetization for non-payers
A14: Refer a friend who signs up | B14: 100 | C14: Growth loop
A16: 🪙 Coins — what you spend them on
A17: Item | B17: Coin Cost | C17: Notes
A18: Extra tarot draw (beyond daily free one) | B18: 30 | C18: Small, frequent sink
A19: Common/Uncommon mineral pack pull | B19: 50 | C19: Core collection loop for free users
A20: Extra companion chat messages | B20: 10 / message (or 100 = 15 msgs) | C20: Bundle discourages micro-spending friction
A21: Companion cosmetic — common tier | B21: 150 | C21: Self-expression sink
A22: Skip a moon-event wait timer | B22: 40 | C22: Classic mobile-game patience sink
A23: Extra Compatibility calculation (Free/Mystic cap) | B23: 25 | C23: Cheap enough to feel fair, frequent enough to add up
A25: 💎 Gems — how you get them
A26: Source | B26: Amount | C26: Notes
A27: Purchased (see Shop Catalog tab for packs) | B27: Varies | C27: Primary IAP revenue driver
A28: Mystic subscription | B28: 300 / month, auto-granted | C28: Makes the subscription feel like more than a paywall key
A29: Oracle subscription | B29: 800 / month, auto-granted | C29: Also unlocks the guaranteed monthly Rare+ pull
A30: Rare achievement milestones (e.g. full mineral set) | B30: 50–200 | C30: Small free drip to keep non-payers engaged with the Gem economy
A32: 💎 Gems — what you spend them on
A33: Item | B33: Gem Cost | C33: Notes
A34: Rare mineral pack pull | B34: 150 | C34: Guaranteed Uncommon+, chance of Rare
A35: Legendary mineral pack pull | B35: 400 | C35: Guaranteed Rare+, chance of Legendary — the whale item
A36: Companion persona / skin — rare tier | B36: 500 | C36: Cosmetic, no gameplay effect — safe monetization
A37: One-time full natal chart deep report | B37: 300 | C37: High perceived value, low marginal cost to deliver
A38: Yearly forecast (non-Oracle one-time unlock) | B38: 600 | C38: Lets Free/Mystic users buy the Oracle-exclusive anchor product without subscribing
A39: Extra Compatibility reading (beyond tier quota) | B39: 100 | C39: Same sink as Coins, priced for impatience
A40: Unlimited chat pass — 30 days (non-subscribers) | B40: 450 | C40: Lets a non-subscriber buy just the chat habit
A41: Remove ads permanently | B41: 250 | C41: One-time, appeals to free users who will never subscribe
A43: Note: all costs above are illustrative starting points, not tested pricing — tune against real conversion data once the app has users. Source: designed for this plan, not benchmarked against a live competitor's exact numbers.

Sheet Shop Catalog
A1: Shop Catalog
A2: What's actually for sale, in real money, and the effective price per Gem/Coin at each pack size (bigger packs = better value, standard mobile-game structure).
A4: 💎 Gem Packs (real-money purchase)
A5: Pack Name | B5: Gems | C5: Bonus | D5: Price (USD) | E5: Effective $ per 100 Gems
A6: Spark | B6: 100 | C6: — | D6: 0.99 | E6: =D6/B6*100 -> 0.99
A7: Glow | B7: 550 | C7: +10% | D7: 4.99 | E7: =D7/B7*100 -> 0.90727273
A8: Radiance | B8: 1200 | C8: +20% | D8: 9.99 | E8: =D8/B8*100 -> 0.8325
A9: Aura | B9: 2500 | C9: +25% | D9: 19.99 | E9: =D9/B9*100 -> 0.7996
A10: Ascendant | B10: 6500 | C10: +30% | D10: 49.99 | E10: =D10/B10*100 -> 0.76907692
A12: 🪙 Coin Bundles (real-money purchase, for impatient free users)
A13: Pack Name | B13: Coins | C13: Bonus | D13: Price (USD) | E13: Effective $ per 1,000 Coins
A14: Pouch | B14: 500 | C14: — | D14: 0.99 | E14: =D14/B14*1000 -> 1.98
A15: Satchel | B15: 3000 | C15: +15% | D15: 4.99 | E15: =D15/B15*1000 -> 1.6633333
A16: Chest | B16: 7000 | C16: +25% | D16: 9.99 | E16: =D16/B16*1000 -> 1.4271429
A18: 🔔 Subscription Plans (recap — see 'Free vs Premium' for full feature detail)
A19: Plan | B19: Price / Month | C19: Price / Year | D19: Gem Stipend / Month | E19: Positioning
A20: Apprentice | B20: Free | C20: Free | D20: 0 | E20: The stars, on a budget.
A21: Mystic | B21: $4.99 | C21: $47.99 (−20%) | D21: 300 | E21: For the mildly obsessed.
A22: Oracle | B22: $9.99 | C22: $95.99 (−20%) | D22: 800 | E22: For those who have made peace with it.
A24: Blue cells (Price USD columns) are editable pricing inputs — the effective-value column recalculates automatically. Annual prices assume a standard 20% loyalty discount vs. paying monthly.

Sheet Chat & Companion
A1: Chat & Companion
A2: The feature that turns 'an app I open' into 'someone I talk to.' Biggest engagement lever in the product — spec it well.
A4: What It Is
A5: Concept | B5: A persistent chat with your Zodiac Companion — a character with a name, a visual look, and a consistent personality (warm, a little dramatic, self-aware and funny about being an app that wants your money).
A6: Powered by | B6: An LLM (e.g. Claude) prompted with the user's sign, current moon phase, recent tarot draws, and Dossier fields — so replies feel personalized, not generic. Companion never gives real medical/legal/financial advice; light guardrails needed here.
A7: Bonding mechanic | B7: A visible 'bond level' or affection meter that rises with chat frequency and streaks, unlocking companion cosmetics and new dialogue — classic companion-app retention design.
A8: Tone guardrails | B8: Sincere > sarcastic on emotionally heavy topics (grief, anxiety); funny and self-aware on lighthearted ones (money, indecision, love drama). Never mock the user's beliefs, only gently mock the business model.
A10: Monetization
A11: Tier | B11: Chat Allowance
A12: Apprentice (Free) | B12: 3 messages/day, then pay 10 Coins/message or wait for reset
A13: Mystic | B13: 30 messages/day included
A14: Oracle | B14: Unlimited
A15: Non-subscriber add-on | B15: 450 Gems = 30-day unlimited chat pass, for people who want just this feature
A17: Why This Matters More Than It Looks Like It Should
A18: Daily-word and horoscope apps churn because the content is static and skippable. A chat relationship is not skippable in the same way — people don't want to 'leave a conversation hanging.' This is the single highest-leverage retention feature in the whole plan, and the message-cap-then-paywall pattern is proven monetization (same shape as companion/romance-sim apps, which convert very well with exactly this demographic).
A23: Build Note
A24: Not built yet in the current app scaffold. Needs: a backend chat endpoint, an LLM API integration, per-user message-count tracking, and moderation/safety guardrails before shipping publicly.

Sheet Content Calendar
A1: Content Calendar & Cadence
A2: What content ships how often, and who/what produces it.
A4: Content Type | B4: Cadence | C4: Source | D4: Notes
A5: Daily word (free) | B5: Daily, per sign | C5: Human writer, AI-assisted draft + human review | D5: Short, punchy, shareable — this is the acquisition engine
A6: Daily reading (premium) | B6: Daily, per sign | C6: Human writer, AI-assisted draft + human review | D6: Longer, more specific, ties to that day's moon phase
A7: Weekly theme | B7: Weekly, per sign | C7: Human writer | D7: Bigger arc, anchors the week's chat conversations
A8: Yearly forecast | B8: Annual, per sign | C8: Senior astrologer/writer, heavily edited | D8: The anchor premium product — treat like a real deliverable, not filler
A9: Moon phase + ritual copy | B9: 8 entries per lunar cycle (~29.5 days) | C9: Written once, reused every cycle with light variation | D9: Already implemented with real astronomical math in the app
A10: Tarot card meanings | B10: Fixed library, 78 cards | C10: Written once (upright + reversed), reused | D10: Scaffold currently has 12 of 78 — needs the full deck
A11: Companion chat responses | B11: Real-time, generated per message | C11: LLM, prompted with user context + brand voice guide | D11: Needs a written 'voice bible' as the system prompt foundation
A12: Mineral collectible lore | B12: Fixed library, grows over time | C12: Written once per mineral, illustrated/sculpted once | D12: This is also the artist/sculptor's most direct creative contribution
A14: Who Owns What
A15: Product / voice / brand | B15: You — positioning, tone, visual identity, companion + mineral art direction
A16: Engineering / systems | B16: Claude — architecture, feature builds, currency/paywall logic, backend integration
A17: Ongoing content | B17: Needs a dedicated writer (or a tight AI-draft + human-edit pipeline) before launch — this is the one recurring cost the plan can't automate away entirely

Sheet Revenue Assumptions
A1: Revenue Assumptions
A2: Every blue cell below is an editable input. Change any of them and the Financial Projections and Unit Economics tabs recalculate automatically.
A4: Growth & Retention
A5: Assumption | B5: Value | C5: Notes / Source
A6: Month 1 new downloads | B6: 5000 | C6: Assumption — set to your actual soft-launch number once you have one
A7: Month-over-month download growth | B7: 0.12 | C7: Assumption — organic + paid acquisition combined
A8: Monthly user churn (all users) | B8: 0.08 | C8: Assumption — astrology/wellness app category benchmark range is roughly 6–12%
A10: Conversion & Pricing
A11: Assumption | B11: Value | C11: Notes / Source
A12: Free-to-paid subscription conversion rate | B12: 0.04 | C12: Assumption — freemium subscription apps commonly land 2–6%
A13: Share of paying users on Mystic | B13: 0.7 | C13: Assumption — cheaper tier usually carries the volume
A14: Share of paying users on Oracle | B14: 0.3 | C14: Assumption — should equal 1 − Mystic share
A15: Mystic monthly price | B15: 4.99 | C15: From Shop Catalog tab
A16: Oracle monthly price | B16: 9.99 | C16: From Shop Catalog tab
A18: In-App Purchases (Gems)
A19: Assumption | B19: Value | C19: Notes / Source
A20: % of free users buying a Gem pack in a given month | B20: 0.03 | C20: Assumption — collectible/rarity pulls are the draw for non-subscribers
A21: Average Gem pack purchase — free users | B21: 4.99 | C21: Assumption — the 'Glow' pack from Shop Catalog
A22: % of subscribers buying extra Gems in a given month | B22: 0.05 | C22: Assumption — whale behavior even among payers
A23: Average extra Gem purchase — subscribers | B23: 9.99 | C23: Assumption — the 'Radiance' pack from Shop Catalog
A25: Unit Economics Inputs
A26: Assumption | B26: Value | C26: Notes / Source
A27: Blended customer acquisition cost (CAC) | B27: 2.5 | C27: Assumption — typical for a niche content/wellness app on paid social; validate with real ad spend once live
A28: Average paying-subscriber lifetime (months) | B28: 8 | C28: Assumption — derived from the churn rate above as a starting estimate
A30: Every yellow cell is a hardcoded planning assumption, not a measured result — none of this is real usage data. Replace with actuals as soon as you have them; the two model tabs will recalculate instantly.

Sheet Financial Projections
A1: Financial Projections — Year 1
A2: Every number below is a formula driven by the 'Revenue Assumptions' tab. Change an assumption there and this whole model updates.
A4: Metric | B4: Month 1 | C4: Month 2 | D4: Month 3 | E4: Month 4 | F4: Month 5 | G4: Month 6 | H4: Month 7 | I4: Month 8 | J4: Month 9 | K4: Month 10 | L4: Month 11 | M4: Month 12
A5: New downloads | B5: ='Revenue Assumptions'!$B$6 -> 5000 | C5: =B5*(1+'Revenue Assumptions'!$B$7) -> 5600 | D5: =C5*(1+'Revenue Assumptions'!$B$7) -> 6272 | E5: =D5*(1+'Revenue Assumptions'!$B$7) -> 7024.64 | F5: =E5*(1+'Revenue Assumptions'!$B$7) -> 7867.5968 | G5: =F5*(1+'Revenue Assumptions'!$B$7) -> 8811.7084 | H5: =G5*(1+'Revenue Assumptions'!$B$7) -> 9869.1134 | I5: =H5*(1+'Revenue Assumptions'!$B$7) -> 11053.407 | J5: =I5*(1+'Revenue Assumptions'!$B$7) -> 12379.816 | ... M5: =L5*(1+'Revenue Assumptions'!$B$7) -> 17392.75
A6: Monthly Active Users (MAU) | B6: =B5 -> 5000 | C6: =B6*(1-'Revenue Assumptions'!$B$8)+C5 -> 10200 | D6: =C6*(1-'Revenue Assumptions'!$B$8)+D5 -> 15656 | E6: =D6*(1-'Revenue Assumptions'!$B$8)+E5 -> 21428.16 | F6: =E6*(1-'Revenue Assumptions'!$B$8)+F5 -> 27581.504 | G6: =F6*(1-'Revenue Assumptions'!$B$8)+G5 -> 34186.692 | H6: =G6*(1-'Revenue Assumptions'!$B$8)+H5 -> 41320.87 | I6: =H6*(1-'Revenue Assumptions'!$B$8)+I5 -> 49068.608 | J6: =I6*(1-'Revenue Assumptions'!$B$8)+J5 -> 57522.935 | ... M6: =L6*(1-'Revenue Assumptions'!$B$8)+M5 -> 88207.74
A7: Paying subscribers | B7: =B6*'Revenue Assumptions'!$B$12 -> 200 | C7: =C6*'Revenue Assumptions'!$B$12 -> 408 | D7: =D6*'Revenue Assumptions'!$B$12 -> 626.24 | E7: =E6*'Revenue Assumptions'!$B$12 -> 857.1264 | F7: =F6*'Revenue Assumptions'!$B$12 -> 1103.2602 | G7: =G6*'Revenue Assumptions'!$B$12 -> 1367.4677 | H7: =H6*'Revenue Assumptions'!$B$12 -> 1652.8348 | I7: =I6*'Revenue Assumptions'!$B$12 -> 1962.7443 | ... M7: =M6*'Revenue Assumptions'!$B$12 -> 3528.3096
A8: Mystic subscribers | B8: =B7*'Revenue Assumptions'!$B$13 -> 140 | C8: =C7*'Revenue Assumptions'!$B$13 -> 285.6 | D8: =D7*'Revenue Assumptions'!$B$13 -> 438.368 | E8: =E7*'Revenue Assumptions'!$B$13 -> 599.98848 | F8: =F7*'Revenue Assumptions'!$B$13 -> 772.28211 | G8: =G7*'Revenue Assumptions'!$B$13 -> 957.22738 | H8: =H7*'Revenue Assumptions'!$B$13 -> 1156.9844 | I8: =I7*'Revenue Assumptions'!$B$13 -> 1373.921 | ... M8: =M7*'Revenue Assumptions'!$B$13 -> 2469.8167
A9: Oracle subscribers | B9: =B7*'Revenue Assumptions'!$B$14 -> 60 | C9: =C7*'Revenue Assumptions'!$B$14 -> 122.4 | D9: =D7*'Revenue Assumptions'!$B$14 -> 187.872 | E9: =E7*'Revenue Assumptions'!$B$14 -> 257.13792 | F9: =F7*'Revenue Assumptions'!$B$14 -> 330.97805 | G9: =G7*'Revenue Assumptions'!$B$14 -> 410.24031 | H9: =H7*'Revenue Assumptions'!$B$14 -> 495.85044 | I9: =I7*'Revenue Assumptions'!$B$14 -> 588.82329 | ... M9: =M7*'Revenue Assumptions'!$B$14 -> 1058.4929
A10: Subscription revenue | B10: =B8*'Revenue Assumptions'!$B$15+B9*'Revenue Assumptions'!$B$16 -> 1298 | C10: =C8*'Revenue Assumptions'!$B$15+C9*'Revenue Assumptions'!$B$16 -> 2647.92 | D10: =D8*'Revenue Assumptions'!$B$15+D9*'Revenue Assumptions'!$B$16 -> 4064.2976 | E10: =E8*'Revenue Assumptions'!$B$15+E9*'Revenue Assumptions'!$B$16 -> 5562.7503 | F10: =F8*'Revenue Assumptions'!$B$15+F9*'Revenue Assumptions'!$B$16 -> 7160.1584 | G10: =G8*'Revenue Assumptions'!$B$15+G9*'Revenue Assumptions'!$B$16 -> 8874.8653 | H10: =H8*'Revenue Assumptions'!$B$15+H9*'Revenue Assumptions'!$B$16 -> 10726.898 | I10: =I8*'Revenue Assumptions'!$B$15+I9*'Revenue Assumptions'!$B$16 -> 12738.211 | ... M10: =M8*'Revenue Assumptions'!$B$15+M9*'Revenue Assumptions'!$B$16 -> 22898.729
A11: Free-user Gem revenue | B11: =(B6-B7)*'Revenue Assumptions'!$B$20*'Revenue Assumptions'!$B$21 -> 718.56 | C11: =(C6-C7)*'Revenue Assumptions'!$B$20*'Revenue Assumptions'!$B$21 -> 1465.8624 | D11: =(D6-D7)*'Revenue Assumptions'!$B$20*'Revenue Assumptions'!$B$21 -> 2249.9551 | E11: =(E6-E7)*'Revenue Assumptions'!$B$20*'Revenue Assumptions'!$B$21 -> 3079.4837 | F11: =(F6-F7)*'Revenue Assumptions'!$B$20*'Revenue Assumptions'!$B$21 -> 3963.7931 | G11: =(G6-G7)*'Revenue Assumptions'!$B$20*'Revenue Assumptions'!$B$21 -> 4913.0379 | H11: =(H6-H7)*'Revenue Assumptions'!$B$20*'Revenue Assumptions'!$B$21 -> 5938.3049 | I11: =(I6-I7)*'Revenue Assumptions'!$B$20*'Revenue Assumptions'!$B$21 -> 7051.7477 | ... M11: =(M6-M7)*'Revenue Assumptions'!$B$20*'Revenue Assumptions'!$B$21 -> 12676.511
A12: Subscriber extra-Gem revenue | B12: =B7*'Revenue Assumptions'!$B$22*'Revenue Assumptions'!$B$23 -> 99.9 | C12: =C7*'Revenue Assumptions'!$B$22*'Revenue Assumptions'!$B$23 -> 203.796 | D12: =D7*'Revenue Assumptions'!$B$22*'Revenue Assumptions'!$B$23 -> 312.80688 | E12: =E7*'Revenue Assumptions'!$B$22*'Revenue Assumptions'!$B$23 -> 428.13464 | F12: =F7*'Revenue Assumptions'!$B$22*'Revenue Assumptions'!$B$23 -> 551.07845 | G12: =G7*'Revenue Assumptions'!$B$22*'Revenue Assumptions'!$B$23 -> 683.05011 | H12: =H7*'Revenue Assumptions'!$B$22*'Revenue Assumptions'!$B$23 -> 825.59099 | I12: =I7*'Revenue Assumptions'!$B$22*'Revenue Assumptions'!$B$23 -> 980.39078 | ... M12: =M7*'Revenue Assumptions'!$B$22*'Revenue Assumptions'!$B$23 -> 1762.3906
A13: Total monthly revenue | B13: =B10+B11+B12 -> 2116.46 | C13: =C10+C11+C12 -> 4317.5784 | D13: =D10+D11+D12 -> 6627.0596 | E13: =E10+E11+E12 -> 9070.3687 | F13: =F10+F11+F12 -> 11675.03 | G13: =G10+G11+G12 -> 14470.953 | H13: =H10+H11+H12 -> 17490.794 | I13: =I10+I11+I12 -> 20770.349 | ... M13: =M10+M11+M12 -> 37337.631
A14: Cumulative revenue | B14: =B13 -> 2116.46 | C14: =B14+C13 -> 6434.0384 | D14: =C14+D13 -> 13061.098 | E14: =D14+E13 -> 22131.467 | F14: =E14+F13 -> 33806.497 | G14: =F14+G13 -> 48277.45 | H14: =G14+H13 -> 65768.244 | I14: =H14+I13 -> 86538.593 | J14: =I14+J13 -> 110887.59 | ... M14: =L14+M13 -> 209077.39
A16: Year 1 Summary
A17: Total Year 1 revenue | B17: =M14 -> 209077.39
A18: Month 12 MAU | B18: =M6 -> 88207.74

Sheet Unit Economics
A1: Unit Economics
A2: LTV, CAC, and payback — the numbers that tell you whether the acquisition math actually works.
A4: Metric | B4: Value | C4: Formula / Explanation
A5: Blended paying ARPU / month | B5: ='Revenue Assumptions'!$B$13*'Revenue Assumptions'!$B$15+'Revenue Assumptions'!$B$14*'Revenue Assumptions'!$B$16 -> 6.49 | C5: Weighted average of Mystic and Oracle pricing by their share of paying users
A6: Average subscriber lifetime (months) | B6: ='Revenue Assumptions'!$B$28 -> 8 | C6: From Revenue Assumptions tab
A7: LTV (subscription only) | B7: =B5*B6 -> 51.92 | C7: Blended ARPU × average lifetime. Excludes Gem/IAP revenue, so this is a conservative floor, not the full picture.
A8: CAC (blended) | B8: ='Revenue Assumptions'!$B$27 -> 2.5 | C8: From Revenue Assumptions tab — cost per install/signup, not per paying user
A9: LTV : CAC ratio | B9: =B7/B8 -> 20.768 | C9: Healthy SaaS/subscription benchmark is roughly 3x or higher. Below 1x means you're losing money on every acquired user.
A10: CAC payback period (months) | B10: =IF(B5=0,"n/a",B8/B5) -> 0.38520801 | C10: How many months of subscription revenue it takes to recoup the acquisition cost of one paying user
A12: This tab only models subscription LTV/CAC, not Gem/IAP revenue per user — a true blended LTV would be higher. Treat this as the conservative case for whether the subscription business alone can work.

Sheet Target Audience & Marketing
A1: Target Audience & Marketing
A2: Who we're building for, and how they find us.
A4: Primary Persona
A5: Who | B5: Women, roughly 18–34, into astrology / tarot / crystals / manifestation / witchy or cottagecore aesthetics
A6: Where they already are | B6: TikTok and Instagram — astrology and tarot content performs extremely well in short-form video; this is a proven, low-cost discovery channel for this exact category
A7: What they already do | B7: Read horoscopes daily (often across multiple apps/sites), follow tarot creators, buy real crystals, journal, use manifestation apps
A8: What they want from an app | B8: To feel SEEN and a little bit entertained — not lectured. Depth when they want it, humor so it never feels precious or preachy.
A9: What makes them pay | B9: A feature that feels personal (the companion, the compatibility reading) and a collection they don't want to abandon (the minerals)
A11: Positioning Statement
A12: For people who check their horoscope even when they say they don't believe in it, Mystic Companion is the zodiac app with an actual personality — daily readings, tarot, a moon calendar, and a companion who chats back, wrapped around a collectible mineral system that makes checking in every day genuinely fun. Unlike Co-Star's cold read or a static horoscope site, ours is a relationship, and it's honest about being a business while it's at it.
A17: Competitor Snapshot
A18: App | B18: What They Do Well | C18: Where We Differ
A19: Co-Star | B19: Sharp, cold, very shareable copy; huge brand recognition | C19: We're warmer and funnier, and we have a real game loop (collection + currency) they don't
A20: The Pattern | B20: Deep, personality-driven readings; strong retention among believers | C20: We're more casual/accessible to entry-level users, plus the companion-chat relationship
A21: Sanctuary | B21: Live human astrologers, chat-based readings | C21: We're software-only (cheaper, scalable) with an AI companion instead of paid human sessions
A22: Nebula | B22: Strong tarot + astrology content depth, aggressive subscription upsells | C22: We lean into humor/self-awareness about monetization instead of hiding it
A24: Acquisition Channels (in priority order)
A25: Channel | B25: Why It Works Here
A26: TikTok/Instagram short-form content | B26: Astrology content has proven organic reach; shareable daily-word cards from the app double as free content
A27: Influencer/creator partnerships (tarot, astrology, witchy lifestyle) | B27: Trusted voices in-category convert better than generic ads for this audience
A28: In-app share loop | B28: The free shareable daily-word card feature is a built-in acquisition engine — every free user is a potential billboard
A29: Paid social (once unit economics are validated) | B29: Only after Unit Economics tab shows a healthy LTV:CAC ratio on organic-heavy early data

Sheet Roadmap
A1: Roadmap
A2: From today's working scaffold to a mature, monetizing product.
A4: Phase | B4: Focus | C4: What Ships
A5: Phase 0 | B5: Brand | C5: Name, companion character design, mineral art direction, visual identity, brand voice guide (this is where the artist/sculptor skillset leads)
A6: Phase 1 — MVP | B6: Core loop (DONE — see 'What We've Built') | C6: Onboarding, sun-sign daily word, moon calendar, single tarot draw, mock subscription wall — all working today
A7: Phase 2 | B7: Engagement systems | C7: Coins & Gems economy, mineral collectible pulls, companion bonding meter, streaks, weekly/yearly content, Companion Chat (MVP)
A8: Phase 3 | B8: Monetization infrastructure | C8: Real backend (Supabase/Firebase), real payments (Stripe Billing + Gem pack purchases), full Compatibility calculator + Dossier gating live
A9: Phase 4 | B9: Scale & polish | C9: Native mobile app (React Native), push notifications, full 78-card tarot deck, expanded mineral library, merch tie-in (sculpted physical minerals for top-tier subscribers)
A10: Phase 5 (conditional) | B10: Real matchmaking | C10: Only if traction justifies it: user-to-user matching instead of calculator-only Compatibility — requires moderation, safety reporting, and likely an 18+ gate
A12: Immediate Next Decisions
A13: 1. Pick a real app name and companion character concept
A14: 2. Choose Supabase vs Firebase for the backend
A15: 3. Set up a Stripe account to move the Upgrade screen from mock to real
A16: 4. Decide who writes ongoing daily/weekly/yearly content (you, a hired writer, or an AI-draft + human-edit pipeline)
A17: 5. Validate the Revenue Assumptions tab against any real numbers you have access to (ad costs, category benchmarks) before treating the projection as more than illustrative
